priv_masker/__init__.py
priv_masker/annotations/__init__.py
priv_masker/annotations/capitalized.py
priv_masker/annotations/currency.py
priv_masker/annotations/day.py
priv_masker/annotations/last_name.py
priv_masker/annotations/mask.py
priv_masker/annotations/month.py
priv_masker/annotations/name.py
priv_masker/annotations/nominal_phrases.py
priv_masker/annotations/number.py
priv_masker/annotations/place_name.py
priv_masker/annotations/stop_words.py
priv_masker/annotations/street_name.py
priv_masker/annotations/year.py
priv_masker/annotations/components/__init__.py
priv_masker/annotations/components/base.py
priv_masker/annotations/components/general.py
priv_masker/data/__init__.py
priv_masker/data/abbrs.csv
priv_masker/data/data_download.py
priv_masker/data/numbers.py
priv_masker/data/obvious_phrases.csv
priv_masker/data/stop_words.txt
priv_masker/data/address/__init__.py
priv_masker/data/address/address.csv
priv_masker/data/address/streets.csv
priv_masker/data/address/docs/places.spacy
priv_masker/data/address/docs/streets.spacy
priv_masker/data/contexts/__init__.py
priv_masker/data/money/__init__.py
priv_masker/data/money/money_codes.py
priv_masker/data/money/money_names.py
priv_masker/data/money/money_symbols.py
priv_masker/data/names/__init__.py
priv_masker/data/names/female_first_name.csv
priv_masker/data/names/female_last_name.csv
priv_masker/data/names/female_second_name.csv
priv_masker/data/names/male_first_name.csv
priv_masker/data/names/male_last_name.csv
priv_masker/data/names/male_second_name.csv
priv_masker/data/names/docs/last_names.spacy
priv_masker/data/names/docs/names.spacy
priv_masker/data/streets/__init__.py
priv_masker/masks/__init__.py
priv_masker/masks/address_masker.py
priv_masker/masks/cash_masker.py
priv_masker/masks/contact_masker.py
priv_masker/masks/date_masker.py
priv_masker/masks/id_numbers_masker.py
priv_masker/masks/invalid_unmasker.py
priv_masker/masks/orgname_masker.py
priv_masker/masks/persname_masker.py
priv_masker-0.4.dist-info/LICENSE.txt
priv_masker-0.4.dist-info/METADATA
priv_masker-0.4.dist-info/WHEEL
priv_masker-0.4.dist-info/top_level.txt
priv_masker-0.4.dist-info/RECORD
