Metadata-Version: 2.1
Name: priv-masker
Version: 0.4
Summary: Text anonymization tool
Home-page: https://github.com/ZILiAT-NASK/PrivMasker
Author: NASK ZILiAT, Adam Nowakowski
Author-email: adam.nowakowski@nask.pl
License: UNKNOWN
Platform: UNKNOWN
License-File: LICENSE.txt
Requires-Dist: numpy (>=1.22.2)
Requires-Dist: spacy (>=3.0)
Requires-Dist: setuptools (>=57.0.0)
Requires-Dist: pandas (>=1.4.1)
Requires-Dist: scipy (>=1.8.0)
